superfsmon/__init__.py
superfsmon/superfsmon.py
superfsmon-1.2.3.dist-info/LICENSE.txt
superfsmon-1.2.3.dist-info/METADATA
superfsmon-1.2.3.dist-info/WHEEL
superfsmon-1.2.3.dist-info/entry_points.txt
superfsmon-1.2.3.dist-info/top_level.txt
superfsmon-1.2.3.dist-info/RECORD
